sWaraNuvad/__init__.py
sWaraNuvad-2.4.dist-info/METADATA
sWaraNuvad-2.4.dist-info/WHEEL
sWaraNuvad-2.4.dist-info/top_level.txt
sWaraNuvad-2.4.dist-info/RECORD
