Metadata-Version: 2.1
Name: sWaraNuvad
Version: 2.4
Summary: Speech translation assistant
Author: Tejas Sonavane
Classifier: Development Status :: 1 - Planning
Classifier: Intended Audience :: Developers
Classifier: Programming Language :: Python :: 3
Classifier: Operating System :: Unix
Classifier: Operating System :: MacOS :: MacOS X
Classifier: Operating System :: Microsoft :: Windows
Requires-Dist: PyAudio
Requires-Dist: SpeechRecognition
Requires-Dist: googletrans
Requires-Dist: pyttsx3
Requires-Dist: translate
